{"format": 1, "version": "4.2", "settings": "fa5ef8c179ea11258b85de8b532ee998", "files": {"forms_py": {"hash": "679a733e64c6c4c16f409ae8005ae605", "index": {"nums": [1, 36, 0, 24, 0, 0, 0], "html_filename": "forms_py.html", "relative_filename": "forms.py"}}, "test_py": {"hash": "ea0192ab5de9b1ec784418539329140b", "index": {"nums": [1, 140, 0, 61, 0, 0, 0], "html_filename": "test_py.html", "relative_filename": "test.py"}}, "views_py": {"hash": "4f1a6347d7aaadc288ce28839b51591c", "index": {"nums": [1, 114, 0, 58, 0, 0, 0], "html_filename": "views_py.html", "relative_filename": "views.py"}}, "_config_py": {"hash": "4bdc11cf73fc31bcd8561093478e7710", "index": {"nums": [1, 7, 0, 0, 0, 0, 0], "html_filename": "_config_py.html", "relative_filename": "_config.py"}}, "models_py": {"hash": "8a84b45e8230fb8cde9e71d5fa452875", "index": {"nums": [1, 33, 0, 8, 0, 0, 0], "html_filename": "models_py.html", "relative_filename": "models.py"}}}}